{
  "bag": "true",
  "true": "true",
  "hat": "true",
  "males": "male",
  "male": "male",
  "man": "male",
  "men": "male",
  "guy": "male",
  "boy": "male",
  "guys": "male",
  "boys": "male",
  "son": "male",
  "sons": "male",
  "father": "male",
  "fathers": "male",
  "dad": "male",
  "dads": "male",
  "husband": "male",
  "brother": "male",
  "brothers": "male",
  "uncle": "male",
  "grandpa": "male",
  "grandfather": "male",
  "woman": "female",
  "female": "female",
  "lady": "female",
  "girl": "female",
  "women": "female",
  "females": "female",
  "ladies": "female",
  "girls": "female",
  "daughter": "female",
  "daughters": "female",
  "mother": "female",
  "mothers": "female",
  "mom": "female",
  "moms": "female",
  "wife": "female",
  "sister": "female",
  "sisters": "female",
  "aunt": "female",
  "grandma": "female",
  "grandmother": "female",
  "t-shirt": "upper_clothes",
  "upper_clothes": "upper_clothes",
  "shirt": "upper_clothes",
  "jacket": "upper_clothes",
  "jumper": "upper_clothes",
  "sweater": "upper_clothes",
  "hoodie": "upper_clothes",
  "polo": "upper_clothes",
  "suit": "upper_clothes",
  "blouse": "upper_clothes",
  "long-sleeved shirt": "upper_clothes",
  "top": "upper_clothes",
  "trousers": "lower_clothes",
  "lower_clothes": "lower_clothes",
  "jeans": "lower_clothes",
  "skirt": "lower_clothes",
  "shorts": "lower_clothes",
  "joggers": "lower_clothes",
  "pants": "lower_clothes",
  "mivia": "roi1_passages",
  "roi1_passages": "roi1_passages",
  "diem": "roi2_passages",
  "roi2_passages": "roi2_passages",
  "without": "negation",
  "negation": "negation",
  "not wearing": "negation",
  "aren't": "negation",
  "are not": "negation",
  "didn't": "negation",
  "not": "negation",
  "don't": "negation",
  "doesn't": "negation",
  "more than": "greater",
  "greater": "greater",
  "more": "greater",
  "over": "greater",
  "above": "greater",
  "exceeding": "greater",
  "upper": "greater",
  "less than": "lower",
  "lower": "lower",
  "less": "lower",
  "under": "lower",
  "below": "lower",
  "equal": "equal",
  "exactly": "equal",
  "precisely": "equal",
  " true": " true",
  "red": "red",
  "blue": "blue",
  "white": "white",
  "pink": "pink",
  "black": "black",
  "brown": "brown",
  "purple": "purple",
  "yellow": "yellow",
  "orange": "orange",
  "gray": "gray",
  "green": "green",
  "ten": "ten",
  "nine": "nine",
  "two": "two",
  "thirty": "thirty",
  "six": "six",
  "one": "one",
  "twelve": "twelve",
  "zero": "zero",
  "four": "four",
  "seven": "seven",
  "eight": "eight",
  "five": "five",
  "three": "three",
  "eleven": "eleven",
  "sixteen": "sixteen",
  "twenty-three": "twenty-three",
  "purle": "purle",
  "brow": "brow",
  "forty": "forty",
  "twenty": "twenty"
}