{
  "bag": " true",
  " true": " true",
  "hat": " true",
  "males": "male",
  "male": "male",
  "man": "male",
  "men": "male",
  "guy": "male",
  "boy": "male",
  "guys": "male",
  "boys": "male",
  "son": "male",
  "sons": "male",
  "father": "male",
  "fathers": "male",
  "dad": "male",
  "dads": "male",
  "husband": "male",
  "brother": "male",
  "brothers": "male",
  "uncle": "male",
  "grandpa": "male",
  "grandfather": "male",
  "woman": "female",
  "female": "female",
  "lady": "female",
  "girl": "female",
  "women": "female",
  "females": "female",
  "ladies": "female",
  "girls": "female",
  "daughter": "female",
  "daughters": "female",
  "mother": "female",
  "mothers": "female",
  "mom": "female",
  "moms": "female",
  "wife": "female",
  "sister": "female",
  "sisters": "female",
  "aunt": "female",
  "grandma": "female",
  "grandmother": "female",
  "t-shirt": "upper_clothes",
  "upper_clothes": "upper_clothes",
  "shirt": "upper_clothes",
  "jacket": "upper_clothes",
  "jumper": "upper_clothes",
  "sweater": "upper_clothes",
  "hoodie": "upper_clothes",
  "polo": "upper_clothes",
  "suit": "upper_clothes",
  "blouse": "upper_clothes",
  "long-sleeved shirt": "upper_clothes",
  "top": "upper_clothes",
  "trousers": "lower_clothes",
  "lower_clothes": "lower_clothes",
  "jeans": "lower_clothes",
  "skirt": "lower_clothes",
  "shorts": "lower_clothes",
  "joggers": "lower_clothes",
  "pants": "lower_clothes",
  "red": "red",
  "blue": "blue",
  "white": "white",
  "pink": "pink",
  "black": "black",
  "brown": "brown",
  "purple": "purple",
  "yellow": "yellow",
  "orange": "orange",
  "green": "green",
  "gray": "gray",
  "true": "true",
  "purle": "purle",
  "brow": "brow"
}